cryptonita/__init__.py
cryptonita/bytestrings.py
cryptonita/conv.py
cryptonita/deps.py
cryptonita/fuzzy_set.py
cryptonita/helpers.py
cryptonita/mixins.py
cryptonita/mod.py
cryptonita/plots.py
cryptonita/space.py
cryptonita/suggesters.py
cryptonita/views.py
cryptonita/attacks/__init__.py
cryptonita/attacks/block_ciphers.py
cryptonita/attacks/mapping.py
cryptonita/attacks/prng.py
cryptonita/metrics/__init__.py
cryptonita/scoring/__init__.py
cryptonita/scoring/freq.py
cryptonita/scoring/score_funcs.py
cryptonita/stats/__init__.py
cryptonita/stats/kasiski.py
cryptonita/toys/__init__.py
cryptonita/toys/substitution_ciphers.py
cryptonita/toys/transposition_ciphers.py
cryptonita/toys/hashes/__init__.py
cryptonita/toys/hashes/keyed.py
cryptonita/toys/hashes/md4.py
cryptonita/toys/hashes/sha1.py
cryptonita/toys/hashes/sha256.py
cryptonita-0.7.0.dist-info/licenses/LICENSE
cryptonita-0.7.0.dist-info/METADATA
cryptonita-0.7.0.dist-info/WHEEL
cryptonita-0.7.0.dist-info/top_level.txt
cryptonita-0.7.0.dist-info/RECORD
