Metadata-Version: 2.4
Name: cryptonita
Version: 0.7.0
Summary: Cryptanalysis swiss army knife
Author: Di Paola Martin
Maintainer: Di Paola Martin
License-Expression: GPL-3.0-only
Project-URL: Homepage, https://github.com/cryptonitas/cryptonita
Project-URL: Repository, https://github.com/cryptonitas/cryptonita
Project-URL: Issues, https://github.com/cryptonitas/cryptonita/issues
Project-URL: Changelog, https://github.com/cryptonitas/cryptonita/releases
Keywords: crypto,cryptography,crypto-analysis
Classifier: Development Status :: 3 - Alpha
Classifier: Intended Audience :: Developers
Classifier: Intended Audience :: Information Technology
Classifier: Intended Audience :: Science/Research
Classifier: Topic :: Scientific/Engineering :: Information Analysis
Classifier: Topic :: Security
Classifier: Topic :: Security :: Cryptography
Classifier: Programming Language :: Python :: 3
Requires-Python: >=3.3
License-File: LICENSE
Requires-Dist: base58
Provides-Extra: full
Requires-Dist: matplotlib; extra == "full"
Requires-Dist: numpy>=2.0; extra == "full"
Requires-Dist: seaborn; extra == "full"
Requires-Dist: pycryptodome; extra == "full"
Requires-Dist: scipy>=1.7.0; extra == "full"
Requires-Dist: langdetect; extra == "full"
Requires-Dist: gmpy2; extra == "full"
Requires-Dist: z3-solver; extra == "full"
Provides-Extra: dev
Requires-Dist: yapf; extra == "dev"
Requires-Dist: twine; extra == "dev"
Requires-Dist: wheel; extra == "dev"
Requires-Dist: coverage; extra == "dev"
Requires-Dist: byexample; extra == "dev"
Requires-Dist: build; extra == "dev"
Dynamic: license-file
